forcefinder/__init__.py
forcefinder/core/__init__.py
forcefinder/core/auto_regularization.py
forcefinder/core/inverse_processing.py
forcefinder/core/response_limit.py
forcefinder/core/source_path_receiver.py
forcefinder/core/sparse_functions.py
forcefinder/core/transient_utilities.py
forcefinder/core/utilities.py
forcefinder/rattlesnake_control_laws/__init__.py
forcefinder/rattlesnake_control_laws/spr_random_control_law.py
forcefinder/transient_quality_evaluation/__init__.py
forcefinder/transient_quality_evaluation/transient_gui_plot.py
forcefinder/transient_quality_evaluation/transient_quality_metrics.py
forcefinder-0.2.2.dist-info/licenses/LICENSE
forcefinder-0.2.2.dist-info/METADATA
forcefinder-0.2.2.dist-info/WHEEL
forcefinder-0.2.2.dist-info/top_level.txt
forcefinder-0.2.2.dist-info/RECORD
