Metadata-Version: 2.4
Name: forcefinder
Version: 0.2.2
Summary: An advanced inverse source estimation package for Python
Home-page: https://github.com/sandialabs/forcefinder
Author: Steven Carter
Author-email: spcarte@sandia.gov
Project-URL: documentation, https://sandialabs.github.io/forcefinder
Classifier: Programming Language :: Python :: 3.11
Classifier: License :: OSI Approved :: GNU General Public License v3 (GPLv3)
Classifier: Natural Language :: English
Classifier: Operating System :: Microsoft :: Windows :: Windows 10
Classifier: Operating System :: Microsoft :: Windows :: Windows 11
Classifier: Operating System :: MacOS :: MacOS X
Requires-Python: >=3.9
License-File: LICENSE
Requires-Dist: numpy>=1.26.0
Requires-Dist: scipy>=1.10.0
Requires-Dist: sdynpy>=0.14.0
Requires-Dist: joblib>=1.3.0
Requires-Dist: matplotlib>=3.5.0
Requires-Dist: cvxpy>=1.7
Requires-Dist: pyqt5
Provides-Extra: dev
Requires-Dist: sdynpy>=0.18.6; extra == "dev"
Requires-Dist: pytest; extra == "dev"
Requires-Dist: pytest-cov; extra == "dev"
Requires-Dist: jupyter-book==1.0.4; extra == "dev"
Requires-Dist: sphinx-autoapi; extra == "dev"
Requires-Dist: nbconvert; extra == "dev"
Dynamic: author
Dynamic: author-email
Dynamic: classifier
Dynamic: description
Dynamic: description-content-type
Dynamic: home-page
Dynamic: license-file
Dynamic: project-url
Dynamic: provides-extra
Dynamic: requires-dist
Dynamic: requires-python
Dynamic: summary
